gsheets_db_connector/__init__.py
gsheets_db_connector/googlesheets.py
gsheets_db_connector-0.4.1.dist-info/LICENSE
gsheets_db_connector-0.4.1.dist-info/METADATA
gsheets_db_connector-0.4.1.dist-info/WHEEL
gsheets_db_connector-0.4.1.dist-info/top_level.txt
gsheets_db_connector-0.4.1.dist-info/RECORD
