Metadata-Version: 2.1
Name: gsheets-db-connector
Version: 0.4.1
Summary: Connects Google sheets to a database connector to transfer information to and fro.
Home-page: https://github.com/fylein/gsheets-db-connector
Author: Shwetabh Kumar
Author-email: shwetabh.kumar@fyle.in
License: MIT
Keywords: fyle,db,python,sdk,sqlite
Platform: UNKNOWN
Classifier: Topic :: Internet :: WWW/HTTP
Classifier: Intended Audience :: Developers
Classifier: Programming Language :: Python :: 3
Classifier: License :: OSI Approved :: MIT License
Classifier: Operating System :: OS Independent
Requires-Dist: logger (==1.4)
Requires-Dist: pandas (==0.25.2)
Requires-Dist: typing (==3.7.4.1)
Requires-Dist: gspread (==3.1.0)
Requires-Dist: google-api-python-client (==1.6.7)
